
<!-- Generated by com.github.maoschanz.DynamicWallpaperEditor -->
<background>
	<starttime>
		<year>2018</year>
		<month>1</month>
		<day>1</day>
		<hour>6</hour>
		<minute>0</minute>
		<second>0</second>
	</starttime>

	<static>
		<file>/home/celson/Imagens/Daka Dibuja Dynamic Wallpaper/daka-dibuja-2-media-noche.jpg</file>
		<duration>9602.0</duration>
	</static>

	<transition type="overlay">
		<duration>6.0</duration>
		<from>/home/celson/Imagens/Daka Dibuja Dynamic Wallpaper/daka-dibuja-2-media-noche.jpg</from>
		<to>/home/celson/Imagens/Daka Dibuja Dynamic Wallpaper/daka-dibuja-3-madrugada.jpg</to>
	</transition>

	<static>
		<file>/home/celson/Imagens/Daka Dibuja Dynamic Wallpaper/daka-dibuja-3-madrugada.jpg</file>
		<duration>9593.0</duration>
	</static>

	<transition type="overlay">
		<duration>6.0</duration>
		<from>/home/celson/Imagens/Daka Dibuja Dynamic Wallpaper/daka-dibuja-3-madrugada.jpg</from>
		<to>/home/celson/Imagens/Daka Dibuja Dynamic Wallpaper/daka-dibuja-4-amanecer.jpg</to>
	</transition>

	<static>
		<file>/home/celson/Imagens/Daka Dibuja Dynamic Wallpaper/daka-dibuja-4-amanecer.jpg</file>
		<duration>9593.0</duration>
	</static>

	<transition type="overlay">
		<duration>6.0</duration>
		<from>/home/celson/Imagens/Daka Dibuja Dynamic Wallpaper/daka-dibuja-4-amanecer.jpg</from>
		<to>/home/celson/Imagens/Daka Dibuja Dynamic Wallpaper/daka-dibuja-5-manana.jpg</to>
	</transition>

	<static>
		<file>/home/celson/Imagens/Daka Dibuja Dynamic Wallpaper/daka-dibuja-5-manana.jpg</file>
		<duration>9593.0</duration>
	</static>

	<transition type="overlay">
		<duration>6.0</duration>
		<from>/home/celson/Imagens/Daka Dibuja Dynamic Wallpaper/daka-dibuja-5-manana.jpg</from>
		<to>/home/celson/Imagens/Daka Dibuja Dynamic Wallpaper/daka-dibuja-6-medio-dia.jpg</to>
	</transition>

	<static>
		<file>/home/celson/Imagens/Daka Dibuja Dynamic Wallpaper/daka-dibuja-6-medio-dia.jpg</file>
		<duration>9593.0</duration>
	</static>

	<transition type="overlay">
		<duration>6.0</duration>
		<from>/home/celson/Imagens/Daka Dibuja Dynamic Wallpaper/daka-dibuja-6-medio-dia.jpg</from>
		<to>/home/celson/Imagens/Daka Dibuja Dynamic Wallpaper/daka-dibuja-7-tarde.jpg</to>
	</transition>

	<static>
		<file>/home/celson/Imagens/Daka Dibuja Dynamic Wallpaper/daka-dibuja-7-tarde.jpg</file>
		<duration>9593.0</duration>
	</static>

	<transition type="overlay">
		<duration>6.0</duration>
		<from>/home/celson/Imagens/Daka Dibuja Dynamic Wallpaper/daka-dibuja-7-tarde.jpg</from>
		<to>/home/celson/Imagens/Daka Dibuja Dynamic Wallpaper/daka-dibuja-8-atardecer.jpg</to>
	</transition>

	<static>
		<file>/home/celson/Imagens/Daka Dibuja Dynamic Wallpaper/daka-dibuja-8-atardecer.jpg</file>
		<duration>9593.0</duration>
	</static>

	<transition type="overlay">
		<duration>6.0</duration>
		<from>/home/celson/Imagens/Daka Dibuja Dynamic Wallpaper/daka-dibuja-8-atardecer.jpg</from>
		<to>/home/celson/Imagens/Daka Dibuja Dynamic Wallpaper/daka-dibuja-1-noche.jpg</to>
	</transition>

	<static>
		<file>/home/celson/Imagens/Daka Dibuja Dynamic Wallpaper/daka-dibuja-1-noche.jpg</file>
		<duration>9593.0</duration>
	</static>

	<transition type="overlay">
		<duration>6.0</duration>
		<from>/home/celson/Imagens/Daka Dibuja Dynamic Wallpaper/daka-dibuja-1-noche.jpg</from>
		<to>/home/celson/Imagens/Daka Dibuja Dynamic Wallpaper/daka-dibuja-2-media-noche (1).jpg</to>
	</transition>

	<static>
		<file>/home/celson/Imagens/Daka Dibuja Dynamic Wallpaper/daka-dibuja-2-media-noche (1).jpg</file>
		<duration>9593.0</duration>
	</static>

	<transition type="overlay">
		<duration>6.0</duration>
		<from>/home/celson/Imagens/Daka Dibuja Dynamic Wallpaper/daka-dibuja-2-media-noche (1).jpg</from>
		<to>/home/celson/Imagens/Daka Dibuja Dynamic Wallpaper/daka-dibuja-2-media-noche.jpg</to>
	</transition>
</background>